glacier_lengths/__init__.py
glacier_lengths/core.py
glacier_lengths/examples.py
glacier_lengths/plotting.py
glacier_lengths-0.1.2.dist-info/LICENSE
glacier_lengths-0.1.2.dist-info/METADATA
glacier_lengths-0.1.2.dist-info/WHEEL
glacier_lengths-0.1.2.dist-info/top_level.txt
glacier_lengths-0.1.2.dist-info/RECORD
