Metadata-Version: 2.1
Name: glacier-lengths
Version: 0.1.2
Summary: Tools to measure glacier lengths statistically
Home-page: https://github.com/erikmannerfelt/glacier_lengths
Author: Erik Schytt Mannerfelt
Author-email: mannerfelt@vaw.baug.ethz.ch
Project-URL: Bug Tracker, https://github.com/erikmannerfelt/glacier_lengths/issues
Classifier: Programming Language :: Python :: 3
Classifier: License :: OSI Approved :: Apache Software License
Classifier: Operating System :: OS Independent
Requires-Python: >=3.7
License-File: LICENSE
Requires-Dist: shapely
Requires-Dist: numpy
Provides-Extra: matplotlib
Requires-Dist: matplotlib ; extra == 'matplotlib'
